jupyterlab_blockly/__init__.py
jupyterlab_blockly/_version.py
jupyterlab_blockly-0.3.3.data/data/share/jupyter/labextensions/jupyterlab-blockly-extension/package.json
jupyterlab_blockly-0.3.3.data/data/share/jupyter/labextensions/jupyterlab-blockly-extension/static/126.8696c3f62d5984998358.js
jupyterlab_blockly-0.3.3.data/data/share/jupyter/labextensions/jupyterlab-blockly-extension/static/126.8696c3f62d5984998358.js.map
jupyterlab_blockly-0.3.3.data/data/share/jupyter/labextensions/jupyterlab-blockly-extension/static/170.8490ee51c8975c5aa4f1.js
jupyterlab_blockly-0.3.3.data/data/share/jupyter/labextensions/jupyterlab-blockly-extension/static/170.8490ee51c8975c5aa4f1.js.map
jupyterlab_blockly-0.3.3.data/data/share/jupyter/labextensions/jupyterlab-blockly-extension/static/190.e603b56a2e2831df011a.js
jupyterlab_blockly-0.3.3.data/data/share/jupyter/labextensions/jupyterlab-blockly-extension/static/190.e603b56a2e2831df011a.js.map
jupyterlab_blockly-0.3.3.data/data/share/jupyter/labextensions/jupyterlab-blockly-extension/static/225.b6e16fa39543258e105e.js
jupyterlab_blockly-0.3.3.data/data/share/jupyter/labextensions/jupyterlab-blockly-extension/static/225.b6e16fa39543258e105e.js.map
jupyterlab_blockly-0.3.3.data/data/share/jupyter/labextensions/jupyterlab-blockly-extension/static/236.6dac205366157ee2b783.js
jupyterlab_blockly-0.3.3.data/data/share/jupyter/labextensions/jupyterlab-blockly-extension/static/236.6dac205366157ee2b783.js.map
jupyterlab_blockly-0.3.3.data/data/share/jupyter/labextensions/jupyterlab-blockly-extension/static/275.cee99caa06517bd4b39f.js
jupyterlab_blockly-0.3.3.data/data/share/jupyter/labextensions/jupyterlab-blockly-extension/static/275.cee99caa06517bd4b39f.js.map
jupyterlab_blockly-0.3.3.data/data/share/jupyter/labextensions/jupyterlab-blockly-extension/static/284.0e8e2a6766734c7b00ab.js
jupyterlab_blockly-0.3.3.data/data/share/jupyter/labextensions/jupyterlab-blockly-extension/static/284.0e8e2a6766734c7b00ab.js.map
jupyterlab_blockly-0.3.3.dist-info/METADATA
jupyterlab_blockly-0.3.3.dist-info/WHEEL
jupyterlab_blockly-0.3.3.dist-info/licenses/LICENSE
jupyterlab_blockly-0.3.3.dist-info/RECORD
