Metadata-Version: 2.3
Name: jupyterlab_blockly
Version: 0.3.3
Dynamic: Keywords
Summary: Blockly extension for JupyterLab.
Project-URL: Homepage, https://github.com/QuantStack/jupyterlab-blockly
Project-URL: Bug Tracker, https://github.com/QuantStack/jupyterlab-blockly/issues
Project-URL: Repository, https://github.com/QuantStack/jupyterlab-blockly
Author: quantstack
License: BSD 3-Clause License
License-File: LICENSE
Classifier: Framework :: Jupyter
Classifier: Framework :: Jupyter :: JupyterLab
Classifier: Framework :: Jupyter :: JupyterLab :: 4
Classifier: Framework :: Jupyter :: JupyterLab :: Extensions
Classifier: Framework :: Jupyter :: JupyterLab :: Extensions :: Prebuilt
Classifier: License :: OSI Approved :: BSD License
Classifier: Programming Language :: Python
Classifier: Programming Language :: Python :: 3
Classifier: Programming Language :: Python :: 3.8
Classifier: Programming Language :: Python :: 3.9
Classifier: Programming Language :: Python :: 3.10
Classifier: Programming Language :: Python :: 3.11
Classifier: Programming Language :: Python :: 3.12
Requires-Python: >=3.8
Requires-Dist: jupyterlab-widgets~=3.0.11
Provides-Extra: dev
Requires-Dist: click; extra == 'dev'
Requires-Dist: jupyter-releaser; extra == 'dev'
Requires-Dist: pre-commit; extra == 'dev'
